CHANGES.txt
README.txt
bootstrap.py
buildout.cfg
setup.py
thoughts.txt
todo.txt
doc/Makefile
doc/conf.py
doc/index.txt
doc/intro.txt
doc/make.bat
doc/model.txt
doc/reference.txt
doc/relation.txt
doc/table.txt
doc/userids.txt
doc/workflow.txt
src/clio/README.txt
src/clio/__init__.py
src/clio/_clio.py
src/clio/interfaces.py
src/clio/sequence.py
src/clio/tests.py
src/clio.egg-info/PKG-INFO
src/clio.egg-info/SOURCES.txt
src/clio.egg-info/dependency_links.txt
src/clio.egg-info/entry_points.txt
src/clio.egg-info/not-zip-safe
src/clio.egg-info/requires.txt
src/clio.egg-info/top_level.txt